{
  "/api/stripe/setup-pricing/route": "app/api/stripe/setup-pricing/route.js",
  "/robots.txt/route": "app/robots.txt/route.js",
  "/sitemap.xml/route": "app/sitemap.xml/route.js",
  "/favicon.ico/route": "app/favicon.ico/route.js",
  "/pricing/opengraph-image/route": "app/pricing/opengraph-image/route.js",
  "/opengraph-image/route": "app/opengraph-image/route.js",
  "/auth/callback/page": "app/auth/callback/page.js",
  "/billing/cancel/page": "app/billing/cancel/page.js",
  "/billing/success/page": "app/billing/success/page.js",
  "/blog/page": "app/blog/page.js",
  "/demo/page": "app/demo/page.js",
  "/features/page": "app/features/page.js",
  "/privacy/page": "app/privacy/page.js",
  "/terms/page": "app/terms/page.js",
  "/_not-found/page": "app/_not-found/page.js",
  "/auth/forgot-password/page": "app/auth/forgot-password/page.js",
  "/auth/login/page": "app/auth/login/page.js",
  "/auth/signup/page": "app/auth/signup/page.js",
  "/auth/update-password/page": "app/auth/update-password/page.js",
  "/page": "app/page.js",
  "/terms-of-service/page": "app/terms-of-service/page.js",
  "/privacy-policy/page": "app/privacy-policy/page.js",
  "/(dashboard)/@modal/(.)properties/[id]/edit/page": "app/(dashboard)/@modal/(.)properties/[id]/edit/page.js",
  "/(dashboard)/dashboard/page": "app/(dashboard)/dashboard/page.js",
  "/api/analytics/web-vitals/route": "app/api/analytics/web-vitals/route.js"
}